{"Exif":{"Lat":52.05277786,"Long":-107.98681310166667,"Date":"2002-09-12T07:12:21-06:00","Tags":{"ApertureValue":4,"Artist":"Geoff Sowrey","Copyright":"© Geoff Sowrey","CreateDate":"2002:09:12 07:12:21","DateTimeOriginal":"2002:09:12 07:12:21","ExposureCompensation|*imagemeta.rat[int32]":"0","ExposureTime|*imagemeta.rat[uint32]":"1/50","FNumber|*imagemeta.rat[uint32]":"4","FileSource|uint8":"3","FocalLength|*imagemeta.rat[uint32]":"337/32","ISO|uint16":"50","ImageDescription":"We awoke next to a turkey farm. It was easily one of our favourite stops on the trip.","LensInfo":"7 70 undef undef","LensModel":"7.0-70.0 mm","Make":"Canon","MaxApertureValue":2.80000199763023,"Model":"Canon PowerShot Pro90 IS","ModifyDate":"2023:05:16 20:03:25","OffsetTime":"-06:00","OffsetTimeDigitized":"-06:00","OffsetTimeOriginal":"-06:00","OwnerName":"Geoff Sowrey","ShutterSpeedValue":0.020000002630836476,"Software":"Adobe Photoshop Lightroom Classic 12.3 (Macintosh)","SubjectDistance|*imagemeta.rat[uint32]":"13107/200"}}}
