{"Exif":{"Lat":51.05267777833333,"Long":-114.172294445,"Date":"2021-09-08T06:51:39-06:00","Tags":{"ApertureValue":1.800000116588115,"Artist":"Geoff Sowrey","BrightnessValue|*imagemeta.rat[int32]":"88501/17089","Copyright":"© Geoff Sowrey","CreateDate":"2021:09:08 06:51:39","DateTimeOriginal":"2021:09:08 06:51:39","ExposureCompensation|*imagemeta.rat[int32]":"0","ExposureTime|*imagemeta.rat[uint32]":"1/120","FNumber|*imagemeta.rat[uint32]":"9/5","FocalLengthIn35mmFormat|uint16":"28","FocalLength|*imagemeta.rat[uint32]":"399/100","ISO|uint16":"50","ImageDescription":"If I walk to work, at just the right time, I get to see this.","LensInfo":"3.9900000095374253 3.9900000095374253 1.8 1.8","LensMake":"Apple","LensModel":"iPhone SE (2nd generation) back camera 3.99mm f/1.8","Make":"Apple","Model":"iPhone SE (2nd generation)","ModifyDate":"2023:05:19 07:30:27","OffsetTime":"-06:00","OffsetTimeDigitized":"-06:00","OffsetTimeOriginal":"-06:00","SceneCaptureType|uint16":"0","SceneType|uint8":"1","ShutterSpeedValue":0.008333330997476868,"Software":"Adobe Photoshop Lightroom Classic 12.3 (Macintosh)","SubSecTimeDigitized|int":"996","SubSecTimeOriginal|int":"996","SubjectArea":"2013 1511 2217 1330"}}}
