{"Exif":{"Lat":43.44288379,"Long":-79.67113563333334,"Date":"2024-10-27T12:34:34-06:00","Tags":{"ApertureValue":8,"Artist":"Geoff Sowrey","BrightnessValue|*imagemeta.rat[int32]":"6071/640","Copyright":"© Geoff Sowrey","CreateDate":"2024:10:27 12:34:34","CustomRendered|uint16":"0","DateTimeOriginal":"2024:10:27 12:34:34","DigitalZoomRatio|*imagemeta.rat[uint32]":"1","ExposureCompensation|*imagemeta.rat[int32]":"0","ExposureTime|*imagemeta.rat[uint32]":"1/500","FNumber|*imagemeta.rat[uint32]":"8","FileSource|uint8":"3","FocalLengthIn35mmFormat|uint16":"24","FocalLength|*imagemeta.rat[uint32]":"24","ISO|uint16":"250","ImageDescription":"This is Oakville Harbour at the end of the season. Most of the boats have been pulled, only a few die hards remain, but they'll be out soon, too. Flooding from heavy rains have led to reinforcement of the banks at the Oakville Club.","LensInfo":"24 70 2.8 2.8","LensModel":"FE 24-70mm F2.8 GM","LightSource|uint16":"0","Make":"SONY","MaxApertureValue":2.7979593450766225,"Model":"ILCE-7M3","ModifyDate":"2024:11:20 21:55:52","OffsetTime":"-07:00","OffsetTimeDigitized":"-06:00","OffsetTimeOriginal":"-06:00","RecommendedExposureIndex|uint32":"250","SceneCaptureType|uint16":"0","SceneType|uint8":"1","SensitivityType|uint16":"2","ShutterSpeedValue":0.002000000394625486,"Software":"Adobe Photoshop Lightroom Classic 14.0.1 (Macintosh)"}}}
