{"Exif":{"Lat":49.279009216666665,"Long":-122.917632455,"Date":"2024-07-15T10:17:30-06:00","Tags":{"ApertureValue":5.600000670860214,"Artist":"Geoff Sowrey","BrightnessValue|*imagemeta.rat[int32]":"10987/1280","Copyright":"© Geoff Sowrey","CreateDate":"2024:07:15 10:17:30","CustomRendered|uint16":"0","DateTimeOriginal":"2024:07:15 10:17:30","DigitalZoomRatio|*imagemeta.rat[uint32]":"1","ExposureCompensation|*imagemeta.rat[int32]":"0","ExposureTime|*imagemeta.rat[uint32]":"1/500","FNumber|*imagemeta.rat[uint32]":"28/5","FileSource|uint8":"3","FocalLengthIn35mmFormat|uint16":"24","FocalLength|*imagemeta.rat[uint32]":"24","ISO|uint16":"250","ImageDescription":"The Quadrangle is perhaps one of Simon Fraser University's most famous parts, a square block encircling (ensquaring?) a geometric garden within, including a stepped pyramid of soil and a koi pond meant to mirror the colour of the nearby Burrard Inlet.","LensInfo":"24 70 2.8 2.8","LensModel":"FE 24-70mm F2.8 GM","LightSource|uint16":"0","Make":"SONY","MaxApertureValue":2.7979593450766225,"Model":"ILCE-7M3","ModifyDate":"2024:07:16 08:13:49","OffsetTime":"-07:00","OffsetTimeDigitized":"-06:00","OffsetTimeOriginal":"-06:00","RecommendedExposureIndex|uint32":"250","SceneCaptureType|uint16":"0","SceneType|uint8":"1","SensitivityType|uint16":"2","ShutterSpeedValue":0.002000000394625486,"Software":"Adobe Photoshop Lightroom Classic 13.4 (Macintosh)"}}}
