{"Exif":{"Lat":53.406336853333336,"Long":-2.9881141016666666,"Date":"2023-03-26T07:48:22-06:00","Tags":{"ApertureValue":8,"Artist":"Geoff Sowrey","BrightnessValue|*imagemeta.rat[int32]":"1071/640","Copyright":"Geoff Sowrey","CreateDate":"2023:03:26 07:48:22","CustomRendered|uint16":"0","DateTimeOriginal":"2023:03:26 07:48:22","DigitalZoomRatio|*imagemeta.rat[uint32]":"1","ExposureCompensation|*imagemeta.rat[int32]":"0","ExposureTime|*imagemeta.rat[uint32]":"1/30","FNumber|*imagemeta.rat[uint32]":"8","FileSource|uint8":"3","FocalLengthIn35mmFormat|uint16":"24","FocalLength|*imagemeta.rat[uint32]":"24","ISO|uint16":"2500","ImageDescription":"John welcomes you to Mathew Street","LensInfo":"24 70 2.8 2.8","LensModel":"FE 24-70mm F2.8 GM","LightSource|uint16":"0","Make":"SONY","MaxApertureValue":2.7979593450766225,"Model":"ILCE-7M3","ModifyDate":"2023:05:19 16:55:44","OffsetTime":"-06:00","OffsetTimeDigitized":"-06:00","OffsetTimeOriginal":"-06:00","RecommendedExposureIndex|uint32":"2500","SceneCaptureType|uint16":"0","SceneType|uint8":"1","SensitivityType|uint16":"2","ShutterSpeedValue":0.033333323989907473,"Software":"Adobe Photoshop Lightroom Classic 12.3 (Macintosh)"}}}
