{"Exif":{"Lat":55.23935399333333,"Long":-6.4494511433333335,"Date":"2025-06-26T11:40:16-06:00","Tags":{"ApertureValue":8.999999991002388,"Artist":"Geoff Sowrey","BrightnessValue|*imagemeta.rat[int32]":"4061/640","Copyright":"© Geoff Sowrey","CreateDate":"2025:06:26 11:40:16","CustomRendered|uint16":"0","DateTimeOriginal":"2025:06:26 11:40:16","DigitalZoomRatio|*imagemeta.rat[uint32]":"1","ExposureCompensation|*imagemeta.rat[int32]":"-1","ExposureTime|*imagemeta.rat[uint32]":"1/250","FNumber|*imagemeta.rat[uint32]":"9","FileSource|uint8":"3","FocalLengthIn35mmFormat|uint16":"51","FocalLength|*imagemeta.rat[uint32]":"51","ISO|uint16":"800","ImageDescription":"Looking along the lush green coast, it's hard not to miss the little white and red cottage, another B\u0026B tucked away from the bustle of nearby towns.","LensInfo":"24 70 2.8 2.8","LensModel":"FE 24-70mm F2.8 GM","LightSource|uint16":"0","Make":"SONY","MaxApertureValue":2.7979593450766225,"Model":"ILCE-7M3","ModifyDate":"2025:07:27 10:30:11","OffsetTime":"-06:00","OffsetTimeDigitized":"-06:00","OffsetTimeOriginal":"-06:00","RecommendedExposureIndex|uint32":"800","SceneCaptureType|uint16":"0","SceneType|uint8":"1","SensitivityType|uint16":"2","ShutterSpeedValue":0.004000000789250969,"Software":"Adobe Photoshop Lightroom Classic 14.4 (Macintosh)"}}}
