{"Exif":{"Lat":59.940811286666666,"Long":30.314583823333333,"Date":"2005-05-03T12:00:38-06:00","Tags":{"Artist":"Geoff Sowrey","Copyright":"© Geoff Sowrey","DateTimeOriginal":"2005:05:03 12:00:38","ISO|uint16":"400","ImageDescription":"I'm not an art expert by any means, but this hallway was astounding in its use of art and design.","LensModel":"Soligor 28-80mm 1:3.5 Macro","Make":"Minolta","Model":"Minolta X-370","ModifyDate":"2023:05:27 22:22:19","OffsetTime":"-06:00","Software":"Adobe Photoshop Lightroom Classic 12.3 (Macintosh)"}}}
