{"Exif":{"Lat":29.663826716666666,"Long":-97.34892356666667,"Date":"1996-04-28T12:00:01-06:00","Tags":{"Artist":"Geoff Sowrey","Copyright":"© Geoff Sowrey","DateTimeOriginal":"1996:04:28 12:00:01","ISO|uint16":"400","ImageDescription":"After having driven through the night through New Mexico and northern Texas, we see the sun moments from cresting the horizon somewhere in the southern parts of the state.","LensModel":"Soligor 28-80mm 1:3.5 Macro","Make":"Minolta","Model":"Minolta X-370","ModifyDate":"2023:05:26 07:05:12","OffsetTime":"-06:00","Software":"Adobe Photoshop Lightroom Classic 12.3 (Macintosh)"}}}
