{"Exif":{"Lat":51.509458065,"Long":-0.135882515,"Date":"2005-04-30T12:00:02-06:00","Tags":{"Artist":"Geoff Sowrey","Copyright":"© Geoff Sowrey","DateTimeOriginal":"2005:04:30 12:00:02","ISO|uint16":"400","ImageDescription":"This little connection between Picadilly (which I'm on) and Regent) where you see the bus) has these amazing bridge/facades of the buildings on Regent. I love the architecture of London.","LensModel":"Minolta 50mm 1:2","Make":"Minolta","Model":"Minolta XG-M","ModifyDate":"2023:05:27 19:03:38","OffsetTime":"-06:00","Software":"Adobe Photoshop Lightroom Classic 12.3 (Macintosh)"}}}
