{"Exif":{"Lat":48.429055,"Long":-123.36791666666667,"Date":"2017-03-28T17:24:06-06:00","Tags":{"ApertureValue":4.999999671145473,"Artist":"Geoff Sowrey","Copyright":"© Geoff Sowrey","CreateDate":"2017:03:28 17:24:06","CustomRendered|uint16":"0","DateTimeOriginal":"2017:03:28 17:24:06","ExposureCompensation|*imagemeta.rat[int32]":"0","ExposureTime|*imagemeta.rat[uint32]":"1/60","FNumber|*imagemeta.rat[uint32]":"5","FocalLength|*imagemeta.rat[uint32]":"24","ISO|uint16":"100","ImageDescription":"Once a hive of scum and villany ... now candles and incense.","LensInfo":"24 70 undef undef","LensModel":"EF24-70mm f/4L IS USM","LensSerialNumber":"4203000680","Make":"Canon","MaxApertureValue":4,"Model":"Canon EOS 70D","ModifyDate":"2023:05:18 21:17:41","OffsetTime":"-06:00","RecommendedExposureIndex|uint32":"100","SceneCaptureType|uint16":"0","SensitivityType|uint16":"2","SerialNumber":"102125000539","ShutterSpeedValue":0.016666661994953737,"Software":"Adobe Photoshop Lightroom Classic 12.3 (Macintosh)","SubSecTimeDigitized|int":"1","SubSecTimeOriginal|int":"1"}}}
